Metadata-Version: 1.0
Name: airflow-faculty-plugin
Version: 0.2.0
Summary: Airflow plugin for interacting with the Faculty platform
Home-page: https://faculty.ai/products-services/platform/
Author: Faculty
Author-email: opensource@faculty.ai
License: Apache Software License
Platform: UNKNOWN
